httpcats/__init__.py
httpcats-1.1.1.dist-info/LICENSE
httpcats-1.1.1.dist-info/METADATA
httpcats-1.1.1.dist-info/WHEEL
httpcats-1.1.1.dist-info/top_level.txt
httpcats-1.1.1.dist-info/RECORD
