Metadata-Version: 2.1
Name: httpcats
Version: 1.1.1
Summary: Get URLs to your favourite HTTP Cats easily!
Home-page: https://github.com/itsmewulf/httpcats
Author: itsmewulf
Author-email: wulf.developer@gmail.com
License: UNKNOWN
Keywords: cat,http,request,api,wrapper
Platform: UNKNOWN
Classifier: Programming Language :: Python :: 3
Classifier: License :: OSI Approved :: MIT License
Classifier: Operating System :: OS Independent
Requires-Python: >=3.6
